LICENSE
MANIFEST.in
README.rst
VERSION
setup.cfg
setup.py
wtforms_webwidgets/__init__.py
wtforms_webwidgets.egg-info/PKG-INFO
wtforms_webwidgets.egg-info/SOURCES.txt
wtforms_webwidgets.egg-info/dependency_links.txt
wtforms_webwidgets.egg-info/not-zip-safe
wtforms_webwidgets.egg-info/requires.txt
wtforms_webwidgets.egg-info/top_level.txt