Metadata-Version: 1.1
Name: wtforms-webwidgets
Version: 0.0.3
Summary: Additional Widgets for WTForms for common web libraries
Home-page: https://github.com/nickw444/wtforms-webwidgets
Author: Nick Whyte
Author-email: nick@nickwhyte.com
License: UNKNOWN
Platform: UNKNOWN
Classifier: Intended Audience :: Developers
Classifier: Programming Language :: Python
Classifier: Environment :: Web Environment
Classifier: Programming Language :: Python :: 3.4
Classifier: Programming Language :: Python :: 3.3
Classifier: Programming Language :: Python :: 2.7
Classifier: Programming Language :: Python :: 2.6
